{
  "matches": [
    {
      "id": "bp-vs-degerfors-r30",
      "title": "IF Brommapojkarna vs Degerfors IF",
      "subtitle": "Allsvenskan Round 30",
      "date": "2025-11-09",
      "folder": "bp-vs-degerfors-r30",
      "video": {
        "type": "hls",
        "parts": {
          "1": "https://api.forzasys.com/allsvenskan/playlist.m3u8/29317:0:6996000/Manifest.m3u8"
        },
        "part2_offset_sec": 2800
      }
    },
    {
      "id": "orgryte-vs-norrkoping-demo",
      "title": "Örgryte IS 3–0 IFK Norrköping",
      "subtitle": "Allsvenskan (demo)",
      "folder": "orgryte-vs-norrkoping-demo"
    },
    {
      "id": "aik-vs-halmstad-demo",
      "title": "AIK 0–2 Halmstads BK",
      "subtitle": "Allsvenskan (demo)",
      "folder": "aik-vs-halmstad-demo"
    },
    {
      "id": "hammarby-vs-elfsborg-demo",
      "title": "Hammarby IF 3–0 IF Elfsborg",
      "subtitle": "Allsvenskan (demo)",
      "folder": "hammarby-vs-elfsborg-demo"
    },
    {
      "id": "goteborg-vs-norrkoping-demo",
      "title": "IFK Göteborg 2–0 IFK Norrköping",
      "subtitle": "Allsvenskan (demo)",
      "folder": "goteborg-vs-norrkoping-demo"
    },
    {
      "id": "chelsea-liverpool-2016",
      "title": "Chelsea 1-2 Liverpool",
      "subtitle": "Premier League 2016-09-16",
      "folder": "chelsea-liverpool-2016",
      "date": "2016-09-16",
      "video": {
        "type": "direct",
        "parts": {
          "1": "/videos/chelsea-liverpool-2016/1.mp4",
          "2": "/videos/chelsea-liverpool-2016/2.mp4"
        }
      }
    },
    {
      "id": "chelsea-liverpool-2016-RAW",
      "title": "Chelsea 1-2 Liverpool (RAW Whisper)",
      "subtitle": "Premier League 2016-09-16 — uncleaned",
      "folder": "chelsea-liverpool-2016-RAW"
    }
  ]
}